LICENSE
MANIFEST.in
README.rst
setup.py
django_yplaces.egg-info/PKG-INFO
django_yplaces.egg-info/SOURCES.txt
django_yplaces.egg-info/dependency_links.txt
django_yplaces.egg-info/requires.txt
django_yplaces.egg-info/top_level.txt
yplaces/__init__.py
yplaces/admin.py
yplaces/forms.py
yplaces/models.py
yplaces/sitemap.py
yplaces/urls.py
yplaces/utils.py
yplaces/views.py
yplaces/api/__init__.py
yplaces/api/__init__.pyc
yplaces/api/handlers.py
yplaces/api/handlers.pyc
yplaces/api/serializers.py
yplaces/api/serializers.pyc
yplaces/api/urls.py
yplaces/api/urls.pyc
yplaces/locale/pt_PT/LC_MESSAGES/django.mo
yplaces/locale/pt_PT/LC_MESSAGES/django.po
yplaces/locale/pt_PT/LC_MESSAGES/djangojs.mo
yplaces/locale/pt_PT/LC_MESSAGES/djangojs.po
yplaces/static/.DS_Store
yplaces/static/yplaces/.DS_Store
yplaces/static/yplaces/css/edit.css
yplaces/static/yplaces/css/index.css
yplaces/static/yplaces/css/photos.css
yplaces/static/yplaces/css/place.css
yplaces/static/yplaces/css/search.css
yplaces/static/yplaces/css/style.css
yplaces/static/yplaces/images/.DS_Store
yplaces/static/yplaces/images/ajax-loader-16x16.gif
yplaces/static/yplaces/images/ajax-loader-200x100.gif
yplaces/static/yplaces/images/ajax-loader.gif
yplaces/static/yplaces/images/default_place_marker.png
yplaces/static/yplaces/images/default_place_picture.png
yplaces/static/yplaces/images/gray-140x140.png
yplaces/static/yplaces/images/photo_placeholder.png
yplaces/static/yplaces/images/star.png
yplaces/static/yplaces/images/star_blank.png
yplaces/static/yplaces/images/star_blank_small.png
yplaces/static/yplaces/images/star_small.png
yplaces/static/yplaces/js/edit.js
yplaces/static/yplaces/js/index.js
yplaces/static/yplaces/js/photos.js
yplaces/static/yplaces/js/place.js
yplaces/static/yplaces/js/search.js
yplaces/static/yplaces/libs/.DS_Store
yplaces/static/yplaces/libs/jquery-1.10.2.min.js
yplaces/static/yplaces/libs/bootstrap-3.0.3/.DS_Store
yplaces/static/yplaces/libs/bootstrap-3.0.3/css/bootstrap-theme.css
yplaces/static/yplaces/libs/bootstrap-3.0.3/css/bootstrap-theme.min.css
yplaces/static/yplaces/libs/bootstrap-3.0.3/css/bootstrap.css
yplaces/static/yplaces/libs/bootstrap-3.0.3/css/bootstrap.min.css
